FPGA/verilog/TEST_ADC_RAMP.v
module TEST_ADC_RAMP (
    input wire clk,
    input wire button,
    output wire [2:0] led,
    output wire [7:0] dac_a_d,
    output wire dac_a_c
);

reg [7:0] ramp = 8'd0, buf1, buf2;

assign dac_a_c = clk;
assign dac_a_d = buf2;
assign led = {ramp[7:6], button};

always @(posedge clk) 
    ramp <= ramp + 1'd1;

always @(negedge clk) begin
    buf1 <= ramp;
    buf2 <= buf1;
end

endmodule

Build_and_Test/testbench/tbDacRamp.v

`include "../verilog/TEST_ADC_RAMP.v"

module tbDacRamp();

reg button_press;
reg clk = 0;

wire [2:0] led_display;
wire [7:0] dac_a_d;
wire dac_a_c;

TEST_ADC_RAMP dut(clk,button_press,led_display,dac_a_d,dac_a_c);

initial begin
    $display("Starting");
    button_press = 1'b0;
    # 100
    button_press = 1'b1;
    # 100
    button_press = 1'b0;
    # 10000
    $finish;
    $display("Finished");
end

// Setup Dump File
initial begin
    $dumpfile("tbDacRamp.vcd");
    $dumpvars(2, tbDacRamp);
end

// Clock
initial forever begin
  #5 clk <= ~clk;
end

endmodule

FPGA/testbench/tbDacRamp.vcd
$date
	Mon Mar 03 14:38:01 2025
$end
$version
	Icarus Verilog
$end
$timescale
	1s
$end
$scope module tbDacRamp $end
$var wire 3 ! led_display [2:0] $end
$var wire 8 " dac_a_d [7:0] $end
$var wire 1 # dac_a_c $end
$var reg 1 $ button_press $end
$var reg 1 % clk $end
$scope module dut $end
$var wire 1 $ button $end
$var wire 1 % clk $end
$var wire 1 # dac_a_c $end
$var wire 8 & dac_a_d [7:0] $end
$var wire 3 ' led [2:0] $end
$var reg 8 ( buf1 [7:0] $end
$var reg 8 ) buf2 [7:0] $end
$var reg 8 * ramp [7:0] $end
$upscope $end
$upscope $end
$enddefinitions $end
$comment Show the parameter values. $end
$dumpall
$end
#0
$dumpvars
b0 *
bx )
b0 (
b0 '
bx &
0%
0$
0#
bx "
b0 !
$end
#5
b1 *
1#
1%
#10
b0 "
b0 &
b0 )
b1 (
0#
0%
#15
b10 *
1#
1%
#20
b1 "
b1 &
b1 )
b10 (
0#
0%
#25
b11 *
1#
1%
#30
b10 "
b10 &
b10 )
b11 (
0#
0%
#35
b100 *
1#
1%
#40
b11 "
b11 &
b11 )
b100 (
0#
0%
#45
b101 *
1#
1%
#50
b100 "
b100 &
b100 )
b101 (
0#
0%
#55
b110 *
1#
1%
#60
b101 "
b101 &
b101 )
b110 (
0#
0%
#65
b111 *
1#
1%
#70
b110 "
b110 &
b110 )
b111 (
0#
0%
#75
b1000 *
1#
1%
#80
b111 "
b111 &
b111 )
b1000 (
0#
0%
#85
b1001 *
1#
1%
#90
b1000 "
b1000 &
b1000 )
b1001 (
0#
0%
#95
b1010 *
1#
1%
#100
b1001 "
b1001 &
b1001 )
b1010 (
0#
0%
b1 !
b1 '
1$
#105
b1011 *
1#
1%
#110
b1010 "
b1010 &
b1010 )
b1011 (
0#
0%
#115
b1100 *
1#
1%
#120
b1011 "
b1011 &
b1011 )
b1100 (
0#
0%
#125
b1101 *
1#
1%
#130
b1100 "
b1100 &
b1100 )
b1101 (
0#
0%
#135
b1110 *
1#
1%
#140
b1101 "
b1101 &
b1101 )
b1110 (
0#
0%
#145
b1111 *
1#
1%
#150
b1110 "
b1110 &
b1110 )
b1111 (
0#
0%
#155
b10000 *
1#
1%
#160
b1111 "
b1111 &
b1111 )
b10000 (
0#
0%
#165
b10001 *
1#
1%
#170
b10000 "
b10000 &
b10000 )
b10001 (
0#
0%
#175
b10010 *
1#
1%
#180
b10001 "
b10001 &
b10001 )
b10010 (
0#
0%
#185
b10011 *
1#
1%
#190
b10010 "
b10010 &
b10010 )
b10011 (
0#
0%
#195
b10100 *
1#
1%
#200
b10011 "
b10011 &
b10011 )
b10100 (
0#
0%
b0 !
b0 '
0$
#205
b10101 *
1#
1%
#210
b10100 "
b10100 &
b10100 )
b10101 (
0#
0%
#215
b10110 *
1#
1%
#220
b10101 "
b10101 &
b10101 )
b10110 (
0#
0%
#225
b10111 *
1#
1%
#230
b10110 "
b10110 &
b10110 )
b10111 (
0#
0%
#235
b11000 *
1#
1%
#240
b10111 "
b10111 &
b10111 )
b11000 (
0#
0%
#245
b11001 *
1#
1%
#250
b11000 "
b11000 &
b11000 )
b11001 (
0#
0%
#255
b11010 *
1#
1%
#260
b11001 "
b11001 &
b11001 )
b11010 (
0#
0%
#265
b11011 *
1#
1%
#270
b11010 "
b11010 &
b11010 )
b11011 (
0#
0%
#275
b11100 *
1#
1%
#280
b11011 "
b11011 &
b11011 )
b11100 (
0#
0%
#285
b11101 *
1#
1%
#290
b11100 "
b11100 &
b11100 )
b11101 (
0#
0%
#295
b11110 *
1#
1%
#300
b11101 "
b11101 &
b11101 )
b11110 (
0#
0%
#305
b11111 *
1#
1%
#310
b11110 "
b11110 &
b11110 )
b11111 (
0#
0%
#315
b100000 *
1#
1%
#320
b11111 "
b11111 &
b11111 )
b100000 (
0#
0%
#325
b100001 *
1#
1%
#330
b100000 "
b100000 &
b100000 )
b100001 (
0#
0%
#335
b100010 *
1#
1%
#340
b100001 "
b100001 &
b100001 )
b100010 (
0#
0%
#345
b100011 *
1#
1%
#350
b100010 "
b100010 &
b100010 )
b100011 (
0#
0%
#355
b100100 *
1#
1%
#360
b100011 "
b100011 &
b100011 )
b100100 (
0#
0%
#365
b100101 *
1#
1%
#370
b100100 "
b100100 &
b100100 )
b100101 (
0#
0%
#375
b100110 *
1#
1%
#380
b100101 "
b100101 &
b100101 )
b100110 (
0#
0%
#385
b100111 *
1#
1%
#390
b100110 "
b100110 &
b100110 )
b100111 (
0#
0%
#395
b101000 *
1#
1%
#400
b100111 "
b100111 &
b100111 )
b101000 (
0#
0%
#405
b101001 *
1#
1%
#410
b101000 "
b101000 &
b101000 )
b101001 (
0#
0%
#415
b101010 *
1#
1%
#420
b101001 "
b101001 &
b101001 )
b101010 (
0#
0%
#425
b101011 *
1#
1%
#430
b101010 "
b101010 &
b101010 )
b101011 (
0#
0%
#435
b101100 *
1#
1%
#440
b101011 "
b101011 &
b101011 )
b101100 (
0#
0%
#445
b101101 *
1#
1%
#450
b101100 "
b101100 &
b101100 )
b101101 (
0#
0%
#455
b101110 *
1#
1%
#460
b101101 "
b101101 &
b101101 )
b101110 (
0#
0%
#465
b101111 *
1#
1%
#470
b101110 "
b101110 &
b101110 )
b101111 (
0#
0%
#475
b110000 *
1#
1%
#480
b101111 "
b101111 &
b101111 )
b110000 (
0#
0%
#485
b110001 *
1#
1%
#490
b110000 "
b110000 &
b110000 )
b110001 (
0#
0%
#495
b110010 *
1#
1%
#500
b110001 "
b110001 &
b110001 )
b110010 (
0#
0%
#505
b110011 *
1#
1%
#510
b110010 "
b110010 &
b110010 )
b110011 (
0#
0%
#515
b110100 *
1#
1%
#520
b110011 "
b110011 &
b110011 )
b110100 (
0#
0%
#525
b110101 *
1#
1%
#530
b110100 "
b110100 &
b110100 )
b110101 (
0#
0%
#535
b110110 *
1#
1%
#540
b110101 "
b110101 &
b110101 )
b110110 (
0#
0%
#545
b110111 *
1#
1%
#550
b110110 "
b110110 &
b110110 )
b110111 (
0#
0%
#555
b111000 *
1#
1%
#560
b110111 "
b110111 &
b110111 )
b111000 (
0#
0%
#565
b111001 *
1#
1%
#570
b111000 "
b111000 &
b111000 )
b111001 (
0#
0%
#575
b111010 *
1#
1%
#580
b111001 "
b111001 &
b111001 )
b111010 (
0#
0%
#585
b111011 *
1#
1%
#590
b111010 "
b111010 &
b111010 )
b111011 (
0#
0%
#595
b111100 *
1#
1%
#600
b111011 "
b111011 &
b111011 )
b111100 (
0#
0%
#605
b111101 *
1#
1%
#610
b111100 "
b111100 &
b111100 )
b111101 (
0#
0%
#615
b111110 *
1#
1%
#620
b111101 "
b111101 &
b111101 )
b111110 (
0#
0%
#625
b111111 *
1#
1%
#630
b111110 "
b111110 &
b111110 )
b111111 (
0#
0%
#635
b10 !
b10 '
b1000000 *
1#
1%
#640
b111111 "
b111111 &
b111111 )
b1000000 (
0#
0%
#645
b1000001 *
1#
1%
#650
b1000000 "
b1000000 &
b1000000 )
b1000001 (
0#
0%
#655
b1000010 *
1#
1%
#660
b1000001 "
b1000001 &
b1000001 )
b1000010 (
0#
0%
#665
b1000011 *
1#
1%
#670
b1000010 "
b1000010 &
b1000010 )
b1000011 (
0#
0%
#675
b1000100 *
1#
1%
#680
b1000011 "
b1000011 &
b1000011 )
b1000100 (
0#
0%
#685
b1000101 *
1#
1%
#690
b1000100 "
b1000100 &
b1000100 )
b1000101 (
0#
0%
#695
b1000110 *
1#
1%
#700
b1000101 "
b1000101 &
b1000101 )
b1000110 (
0#
0%
#705
b1000111 *
1#
1%
#710
b1000110 "
b1000110 &
b1000110 )
b1000111 (
0#
0%
#715
b1001000 *
1#
1%
#720
b1000111 "
b1000111 &
b1000111 )
b1001000 (
0#
0%
#725
b1001001 *
1#
1%
#730
b1001000 "
b1001000 &
b1001000 )
b1001001 (
0#
0%
#735
b1001010 *
1#
1%
#740
b1001001 "
b1001001 &
b1001001 )
b1001010 (
0#
0%
#745
b1001011 *
1#
1%
#750
b1001010 "
b1001010 &
b1001010 )
b1001011 (
0#
0%
#755
b1001100 *
1#
1%
#760
b1001011 "
b1001011 &
b1001011 )
b1001100 (
0#
0%
#765
b1001101 *
1#
1%
#770
b1001100 "
b1001100 &
b1001100 )
b1001101 (
0#
0%
#775
b1001110 *
1#
1%
#780
b1001101 "
b1001101 &
b1001101 )
b1001110 (
0#
0%
#785
b1001111 *
1#
1%
#790
b1001110 "
b1001110 &
b1001110 )
b1001111 (
0#
0%
#795
b1010000 *
1#
1%
#800
b1001111 "
b1001111 &
b1001111 )
b1010000 (
0#
0%
#805
b1010001 *
1#
1%
#810
b1010000 "
b1010000 &
b1010000 )
b1010001 (
0#
0%
#815
b1010010 *
1#
1%
#820
b1010001 "
b1010001 &
b1010001 )
b1010010 (
0#
0%
#825
b1010011 *
1#
1%
#830
b1010010 "
b1010010 &
b1010010 )
b1010011 (
0#
0%
#835
b1010100 *
1#
1%
#840
b1010011 "
b1010011 &
b1010011 )
b1010100 (
0#
0%
#845
b1010101 *
1#
1%
#850
b1010100 "
b1010100 &
b1010100 )
b1010101 (
0#
0%
#855
b1010110 *
1#
1%
#860
b1010101 "
b1010101 &
b1010101 )
b1010110 (
0#
0%
#865
b1010111 *
1#
1%
#870
b1010110 "
b1010110 &
b1010110 )
b1010111 (
0#
0%
#875
b1011000 *
1#
1%
#880
b1010111 "
b1010111 &
b1010111 )
b1011000 (
0#
0%
#885
b1011001 *
1#
1%
#890
b1011000 "
b1011000 &
b1011000 )
b1011001 (
0#
0%
#895
b1011010 *
1#
1%
#900
b1011001 "
b1011001 &
b1011001 )
b1011010 (
0#
0%
#905
b1011011 *
1#
1%
#910
b1011010 "
b1011010 &
b1011010 )
b1011011 (
0#
0%
#915
b1011100 *
1#
1%
#920
b1011011 "
b1011011 &
b1011011 )
b1011100 (
0#
0%
#925
b1011101 *
1#
1%
#930
b1011100 "
b1011100 &
b1011100 )
b1011101 (
0#
0%
#935
b1011110 *
1#
1%
#940
b1011101 "
b1011101 &
b1011101 )
b1011110 (
0#
0%
#945
b1011111 *
1#
1%
#950
b1011110 "
b1011110 &
b1011110 )
b1011111 (
0#
0%
#955
b1100000 *
1#
1%
#960
b1011111 "
b1011111 &
b1011111 )
b1100000 (
0#
0%
#965
b1100001 *
1#
1%
#970
b1100000 "
b1100000 &
b1100000 )
b1100001 (
0#
0%
#975
b1100010 *
1#
1%
#980
b1100001 "
b1100001 &
b1100001 )
b1100010 (
0#
0%
#985
b1100011 *
1#
1%
#990
b1100010 "
b1100010 &
b1100010 )
b1100011 (
0#
0%
#995
b1100100 *
1#
1%
#1000
b1100011 "
b1100011 &
b1100011 )
b1100100 (
0#
0%
#1005
b1100101 *
1#
1%
#1010
b1100100 "
b1100100 &
b1100100 )
b1100101 (
0#
0%
#1015
b1100110 *
1#
1%
#1020
b1100101 "
b1100101 &
b1100101 )
b1100110 (
0#
0%
#1025
b1100111 *
1#
1%
#1030
b1100110 "
b1100110 &
b1100110 )
b1100111 (
0#
0%
#1035
b1101000 *
1#
1%
#1040
b1100111 "
b1100111 &
b1100111 )
b1101000 (
0#
0%
#1045
b1101001 *
1#
1%
#1050
b1101000 "
b1101000 &
b1101000 )
b1101001 (
0#
0%
#1055
b1101010 *
1#
1%
#1060
b1101001 "
b1101001 &
b1101001 )
b1101010 (
0#
0%
#1065
b1101011 *
1#
1%
#1070
b1101010 "
b1101010 &
b1101010 )
b1101011 (
0#
0%
#1075
b1101100 *
1#
1%
#1080
b1101011 "
b1101011 &
b1101011 )
b1101100 (
0#
0%
#1085
b1101101 *
1#
1%
#1090
b1101100 "
b1101100 &
b1101100 )
b1101101 (
0#
0%
#1095
b1101110 *
1#
1%
#1100
b1101101 "
b1101101 &
b1101101 )
b1101110 (
0#
0%
#1105
b1101111 *
1#
1%
#1110
b1101110 "
b1101110 &
b1101110 )
b1101111 (
0#
0%
#1115
b1110000 *
1#
1%
#1120
b1101111 "
b1101111 &
b1101111 )
b1110000 (
0#
0%
#1125
b1110001 *
1#
1%
#1130
b1110000 "
b1110000 &
b1110000 )
b1110001 (
0#
0%
#1135
b1110010 *
1#
1%
#1140
b1110001 "
b1110001 &
b1110001 )
b1110010 (
0#
0%
#1145
b1110011 *
1#
1%
#1150
b1110010 "
b1110010 &
b1110010 )
b1110011 (
0#
0%
#1155
b1110100 *
1#
1%
#1160
b1110011 "
b1110011 &
b1110011 )
b1110100 (
0#
0%
#1165
b1110101 *
1#
1%
#1170
b1110100 "
b1110100 &
b1110100 )
b1110101 (
0#
0%
#1175
b1110110 *
1#
1%
#1180
b1110101 "
b1110101 &
b1110101 )
b1110110 (
0#
0%
#1185
b1110111 *
1#
1%
#1190
b1110110 "
b1110110 &
b1110110 )
b1110111 (
0#
0%
#1195
b1111000 *
1#
1%
#1200
b1110111 "
b1110111 &
b1110111 )
b1111000 (
0#
0%
#1205
b1111001 *
1#
1%
#1210
b1111000 "
b1111000 &
b1111000 )
b1111001 (
0#
0%
#1215
b1111010 *
1#
1%
#1220
b1111001 "
b1111001 &
b1111001 )
b1111010 (
0#
0%
#1225
b1111011 *
1#
1%
#1230
b1111010 "
b1111010 &
b1111010 )
b1111011 (
0#
0%
#1235
b1111100 *
1#
1%
#1240
b1111011 "
b1111011 &
b1111011 )
b1111100 (
0#
0%
#1245
b1111101 *
1#
1%
#1250
b1111100 "
b1111100 &
b1111100 )
b1111101 (
0#
0%
#1255
b1111110 *
1#
1%
#1260
b1111101 "
b1111101 &
b1111101 )
b1111110 (
0#
0%
#1265
b1111111 *
1#
1%
#1270
b1111110 "
b1111110 &
b1111110 )
b1111111 (
0#
0%
#1275
b100 !
b100 '
b10000000 *
1#
1%
#1280
b1111111 "
b1111111 &
b1111111 )
b10000000 (
0#
0%
#1285
b10000001 *
1#
1%
#1290
b10000000 "
b10000000 &
b10000000 )
b10000001 (
0#
0%
#1295
b10000010 *
1#
1%
#1300
b10000001 "
b10000001 &
b10000001 )
b10000010 (
0#
0%
#1305
b10000011 *
1#
1%
#1310
b10000010 "
b10000010 &
b10000010 )
b10000011 (
0#
0%
#1315
b10000100 *
1#
1%
#1320
b10000011 "
b10000011 &
b10000011 )
b10000100 (
0#
0%
#1325
b10000101 *
1#
1%
#1330
b10000100 "
b10000100 &
b10000100 )
b10000101 (
0#
0%
#1335
b10000110 *
1#
1%
#1340
b10000101 "
b10000101 &
b10000101 )
b10000110 (
0#
0%
#1345
b10000111 *
1#
1%
#1350
b10000110 "
b10000110 &
b10000110 )
b10000111 (
0#
0%
#1355
b10001000 *
1#
1%
#1360
b10000111 "
b10000111 &
b10000111 )
b10001000 (
0#
0%
#1365
b10001001 *
1#
1%
#1370
b10001000 "
b10001000 &
b10001000 )
b10001001 (
0#
0%
#1375
b10001010 *
1#
1%
#1380
b10001001 "
b10001001 &
b10001001 )
b10001010 (
0#
0%
#1385
b10001011 *
1#
1%
#1390
b10001010 "
b10001010 &
b10001010 )
b10001011 (
0#
0%
#1395
b10001100 *
1#
1%
#1400
b10001011 "
b10001011 &
b10001011 )
b10001100 (
0#
0%
#1405
b10001101 *
1#
1%
#1410
b10001100 "
b10001100 &
b10001100 )
b10001101 (
0#
0%
#1415
b10001110 *
1#
1%
#1420
b10001101 "
b10001101 &
b10001101 )
b10001110 (
0#
0%
#1425
b10001111 *
1#
1%
#1430
b10001110 "
b10001110 &
b10001110 )
b10001111 (
0#
0%
#1435
b10010000 *
1#
1%
#1440
b10001111 "
b10001111 &
b10001111 )
b10010000 (
0#
0%
#1445
b10010001 *
1#
1%
#1450
b10010000 "
b10010000 &
b10010000 )
b10010001 (
0#
0%
#1455
b10010010 *
1#
1%
#1460
b10010001 "
b10010001 &
b10010001 )
b10010010 (
0#
0%
#1465
b10010011 *
1#
1%
#1470
b10010010 "
b10010010 &
b10010010 )
b10010011 (
0#
0%
#1475
b10010100 *
1#
1%
#1480
b10010011 "
b10010011 &
b10010011 )
b10010100 (
0#
0%
#1485
b10010101 *
1#
1%
#1490
b10010100 "
b10010100 &
b10010100 )
b10010101 (
0#
0%
#1495
b10010110 *
1#
1%
#1500
b10010101 "
b10010101 &
b10010101 )
b10010110 (
0#
0%
#1505
b10010111 *
1#
1%
#1510
b10010110 "
b10010110 &
b10010110 )
b10010111 (
0#
0%
#1515
b10011000 *
1#
1%
#1520
b10010111 "
b10010111 &
b10010111 )
b10011000 (
0#
0%
#1525
b10011001 *
1#
1%
#1530
b10011000 "
b10011000 &
b10011000 )
b10011001 (
0#
0%
#1535
b10011010 *
1#
1%
#1540
b10011001 "
b10011001 &
b10011001 )
b10011010 (
0#
0%
#1545
b10011011 *
1#
1%
#1550
b10011010 "
b10011010 &
b10011010 )
b10011011 (
0#
0%
#1555
b10011100 *
1#
1%
#1560
b10011011 "
b10011011 &
b10011011 )
b10011100 (
0#
0%
#1565
b10011101 *
1#
1%
#1570
b10011100 "
b10011100 &
b10011100 )
b10011101 (
0#
0%
#1575
b10011110 *
1#
1%
#1580
b10011101 "
b10011101 &
b10011101 )
b10011110 (
0#
0%
#1585
b10011111 *
1#
1%
#1590
b10011110 "
b10011110 &
b10011110 )
b10011111 (
0#
0%
#1595
b10100000 *
1#
1%
#1600
b10011111 "
b10011111 &
b10011111 )
b10100000 (
0#
0%
#1605
b10100001 *
1#
1%
#1610
b10100000 "
b10100000 &
b10100000 )
b10100001 (
0#
0%
#1615
b10100010 *
1#
1%
#1620
b10100001 "
b10100001 &
b10100001 )
b10100010 (
0#
0%
#1625
b10100011 *
1#
1%
#1630
b10100010 "
b10100010 &
b10100010 )
b10100011 (
0#
0%
#1635
b10100100 *
1#
1%
#1640
b10100011 "
b10100011 &
b10100011 )
b10100100 (
0#
0%
#1645
b10100101 *
1#
1%
#1650
b10100100 "
b10100100 &
b10100100 )
b10100101 (
0#
0%
#1655
b10100110 *
1#
1%
#1660
b10100101 "
b10100101 &
b10100101 )
b10100110 (
0#
0%
#1665
b10100111 *
1#
1%
#1670
b10100110 "
b10100110 &
b10100110 )
b10100111 (
0#
0%
#1675
b10101000 *
1#
1%
#1680
b10100111 "
b10100111 &
b10100111 )
b10101000 (
0#
0%
#1685
b10101001 *
1#
1%
#1690
b10101000 "
b10101000 &
b10101000 )
b10101001 (
0#
0%
#1695
b10101010 *
1#
1%
#1700
b10101001 "
b10101001 &
b10101001 )
b10101010 (
0#
0%
#1705
b10101011 *
1#
1%
#1710
b10101010 "
b10101010 &
b10101010 )
b10101011 (
0#
0%
#1715
b10101100 *
1#
1%
#1720
b10101011 "
b10101011 &
b10101011 )
b10101100 (
0#
0%
#1725
b10101101 *
1#
1%
#1730
b10101100 "
b10101100 &
b10101100 )
b10101101 (
0#
0%
#1735
b10101110 *
1#
1%
#1740
b10101101 "
b10101101 &
b10101101 )
b10101110 (
0#
0%
#1745
b10101111 *
1#
1%
#1750
b10101110 "
b10101110 &
b10101110 )
b10101111 (
0#
0%
#1755
b10110000 *
1#
1%
#1760
b10101111 "
b10101111 &
b10101111 )
b10110000 (
0#
0%
#1765
b10110001 *
1#
1%
#1770
b10110000 "
b10110000 &
b10110000 )
b10110001 (
0#
0%
#1775
b10110010 *
1#
1%
#1780
b10110001 "
b10110001 &
b10110001 )
b10110010 (
0#
0%
#1785
b10110011 *
1#
1%
#1790
b10110010 "
b10110010 &
b10110010 )
b10110011 (
0#
0%
#1795
b10110100 *
1#
1%
#1800
b10110011 "
b10110011 &
b10110011 )
b10110100 (
0#
0%
#1805
b10110101 *
1#
1%
#1810
b10110100 "
b10110100 &
b10110100 )
b10110101 (
0#
0%
#1815
b10110110 *
1#
1%
#1820
b10110101 "
b10110101 &
b10110101 )
b10110110 (
0#
0%
#1825
b10110111 *
1#
1%
#1830
b10110110 "
b10110110 &
b10110110 )
b10110111 (
0#
0%
#1835
b10111000 *
1#
1%
#1840
b10110111 "
b10110111 &
b10110111 )
b10111000 (
0#
0%
#1845
b10111001 *
1#
1%
#1850
b10111000 "
b10111000 &
b10111000 )
b10111001 (
0#
0%
#1855
b10111010 *
1#
1%
#1860
b10111001 "
b10111001 &
b10111001 )
b10111010 (
0#
0%
#1865
b10111011 *
1#
1%
#1870
b10111010 "
b10111010 &
b10111010 )
b10111011 (
0#
0%
#1875
b10111100 *
1#
1%
#1880
b10111011 "
b10111011 &
b10111011 )
b10111100 (
0#
0%
#1885
b10111101 *
1#
1%
#1890
b10111100 "
b10111100 &
b10111100 )
b10111101 (
0#
0%
#1895
b10111110 *
1#
1%
#1900
b10111101 "
b10111101 &
b10111101 )
b10111110 (
0#
0%
#1905
b10111111 *
1#
1%
#1910
b10111110 "
b10111110 &
b10111110 )
b10111111 (
0#
0%
#1915
b110 !
b110 '
b11000000 *
1#
1%
#1920
b10111111 "
b10111111 &
b10111111 )
b11000000 (
0#
0%
#1925
b11000001 *
1#
1%
#1930
b11000000 "
b11000000 &
b11000000 )
b11000001 (
0#
0%
#1935
b11000010 *
1#
1%
#1940
b11000001 "
b11000001 &
b11000001 )
b11000010 (
0#
0%
#1945
b11000011 *
1#
1%
#1950
b11000010 "
b11000010 &
b11000010 )
b11000011 (
0#
0%
#1955
b11000100 *
1#
1%
#1960
b11000011 "
b11000011 &
b11000011 )
b11000100 (
0#
0%
#1965
b11000101 *
1#
1%
#1970
b11000100 "
b11000100 &
b11000100 )
b11000101 (
0#
0%
#1975
b11000110 *
1#
1%
#1980
b11000101 "
b11000101 &
b11000101 )
b11000110 (
0#
0%
#1985
b11000111 *
1#
1%
#1990
b11000110 "
b11000110 &
b11000110 )
b11000111 (
0#
0%
#1995
b11001000 *
1#
1%
#2000
b11000111 "
b11000111 &
b11000111 )
b11001000 (
0#
0%
#2005
b11001001 *
1#
1%
#2010
b11001000 "
b11001000 &
b11001000 )
b11001001 (
0#
0%
#2015
b11001010 *
1#
1%
#2020
b11001001 "
b11001001 &
b11001001 )
b11001010 (
0#
0%
#2025
b11001011 *
1#
1%
#2030
b11001010 "
b11001010 &
b11001010 )
b11001011 (
0#
0%
#2035
b11001100 *
1#
1%
#2040
b11001011 "
b11001011 &
b11001011 )
b11001100 (
0#
0%
#2045
b11001101 *
1#
1%
#2050
b11001100 "
b11001100 &
b11001100 )
b11001101 (
0#
0%
#2055
b11001110 *
1#
1%
#2060
b11001101 "
b11001101 &
b11001101 )
b11001110 (
0#
0%
#2065
b11001111 *
1#
1%
#2070
b11001110 "
b11001110 &
b11001110 )
b11001111 (
0#
0%
#2075
b11010000 *
1#
1%
#2080
b11001111 "
b11001111 &
b11001111 )
b11010000 (
0#
0%
#2085
b11010001 *
1#
1%
#2090
b11010000 "
b11010000 &
b11010000 )
b11010001 (
0#
0%
#2095
b11010010 *
1#
1%
#2100
b11010001 "
b11010001 &
b11010001 )
b11010010 (
0#
0%
#2105
b11010011 *
1#
1%
#2110
b11010010 "
b11010010 &
b11010010 )
b11010011 (
0#
0%
#2115
b11010100 *
1#
1%
#2120
b11010011 "
b11010011 &
b11010011 )
b11010100 (
0#
0%
#2125
b11010101 *
1#
1%
#2130
b11010100 "
b11010100 &
b11010100 )
b11010101 (
0#
0%
#2135
b11010110 *
1#
1%
#2140
b11010101 "
b11010101 &
b11010101 )
b11010110 (
0#
0%
#2145
b11010111 *
1#
1%
#2150
b11010110 "
b11010110 &
b11010110 )
b11010111 (
0#
0%
#2155
b11011000 *
1#
1%
#2160
b11010111 "
b11010111 &
b11010111 )
b11011000 (
0#
0%
#2165
b11011001 *
1#
1%
#2170
b11011000 "
b11011000 &
b11011000 )
b11011001 (
0#
0%
#2175
b11011010 *
1#
1%
#2180
b11011001 "
b11011001 &
b11011001 )
b11011010 (
0#
0%
#2185
b11011011 *
1#
1%
#2190
b11011010 "
b11011010 &
b11011010 )
b11011011 (
0#
0%
#2195
b11011100 *
1#
1%
#2200
b11011011 "
b11011011 &
b11011011 )
b11011100 (
0#
0%
#2205
b11011101 *
1#
1%
#2210
b11011100 "
b11011100 &
b11011100 )
b11011101 (
0#
0%
#2215
b11011110 *
1#
1%
#2220
b11011101 "
b11011101 &
b11011101 )
b11011110 (
0#
0%
#2225
b11011111 *
1#
1%
#2230
b11011110 "
b11011110 &
b11011110 )
b11011111 (
0#
0%
#2235
b11100000 *
1#
1%
#2240
b11011111 "
b11011111 &
b11011111 )
b11100000 (
0#
0%
#2245
b11100001 *
1#
1%
#2250
b11100000 "
b11100000 &
b11100000 )
b11100001 (
0#
0%
#2255
b11100010 *
1#
1%
#2260
b11100001 "
b11100001 &
b11100001 )
b11100010 (
0#
0%
#2265
b11100011 *
1#
1%
#2270
b11100010 "
b11100010 &
b11100010 )
b11100011 (
0#
0%
#2275
b11100100 *
1#
1%
#2280
b11100011 "
b11100011 &
b11100011 )
b11100100 (
0#
0%
#2285
b11100101 *
1#
1%
#2290
b11100100 "
b11100100 &
b11100100 )
b11100101 (
0#
0%
#2295
b11100110 *
1#
1%
#2300
b11100101 "
b11100101 &
b11100101 )
b11100110 (
0#
0%
#2305
b11100111 *
1#
1%
#2310
b11100110 "
b11100110 &
b11100110 )
b11100111 (
0#
0%
#2315
b11101000 *
1#
1%
#2320
b11100111 "
b11100111 &
b11100111 )
b11101000 (
0#
0%
#2325
b11101001 *
1#
1%
#2330
b11101000 "
b11101000 &
b11101000 )
b11101001 (
0#
0%
#2335
b11101010 *
1#
1%
#2340
b11101001 "
b11101001 &
b11101001 )
b11101010 (
0#
0%
#2345
b11101011 *
1#
1%
#2350
b11101010 "
b11101010 &
b11101010 )
b11101011 (
0#
0%
#2355
b11101100 *
1#
1%
#2360
b11101011 "
b11101011 &
b11101011 )
b11101100 (
0#
0%
#2365
b11101101 *
1#
1%
#2370
b11101100 "
b11101100 &
b11101100 )
b11101101 (
0#
0%
#2375
b11101110 *
1#
1%
#2380
b11101101 "
b11101101 &
b11101101 )
b11101110 (
0#
0%
#2385
b11101111 *
1#
1%
#2390
b11101110 "
b11101110 &
b11101110 )
b11101111 (
0#
0%
#2395
b11110000 *
1#
1%
#2400
b11101111 "
b11101111 &
b11101111 )
b11110000 (
0#
0%
#2405
b11110001 *
1#
1%
#2410
b11110000 "
b11110000 &
b11110000 )
b11110001 (
0#
0%
#2415
b11110010 *
1#
1%
#2420
b11110001 "
b11110001 &
b11110001 )
b11110010 (
0#
0%
#2425
b11110011 *
1#
1%
#2430
b11110010 "
b11110010 &
b11110010 )
b11110011 (
0#
0%
#2435
b11110100 *
1#
1%
#2440
b11110011 "
b11110011 &
b11110011 )
b11110100 (
0#
0%
#2445
b11110101 *
1#
1%
#2450
b11110100 "
b11110100 &
b11110100 )
b11110101 (
0#
0%
#2455
b11110110 *
1#
1%
#2460
b11110101 "
b11110101 &
b11110101 )
b11110110 (
0#
0%
#2465
b11110111 *
1#
1%
#2470
b11110110 "
b11110110 &
b11110110 )
b11110111 (
0#
0%
#2475
b11111000 *
1#
1%
#2480
b11110111 "
b11110111 &
b11110111 )
b11111000 (
0#
0%
#2485
b11111001 *
1#
1%
#2490
b11111000 "
b11111000 &
b11111000 )
b11111001 (
0#
0%
#2495
b11111010 *
1#
1%
#2500
b11111001 "
b11111001 &
b11111001 )
b11111010 (
0#
0%
#2505
b11111011 *
1#
1%
#2510
b11111010 "
b11111010 &
b11111010 )
b11111011 (
0#
0%
#2515
b11111100 *
1#
1%
#2520
b11111011 "
b11111011 &
b11111011 )
b11111100 (
0#
0%
#2525
b11111101 *
1#
1%
#2530
b11111100 "
b11111100 &
b11111100 )
b11111101 (
0#
0%
#2535
b11111110 *
1#
1%
#2540
b11111101 "
b11111101 &
b11111101 )
b11111110 (
0#
0%
#2545
b11111111 *
1#
1%
#2550
b11111110 "
b11111110 &
b11111110 )
b11111111 (
0#
0%
#2555
b0 !
b0 '
b0 *
1#
1%
#2560
b11111111 "
b11111111 &
b11111111 )
b0 (
0#
0%
#2565
b1 *
1#
1%
#2570
b0 "
b0 &
b0 )
b1 (
0#
0%
#2575
b10 *
1#
1%
#2580
b1 "
b1 &
b1 )
b10 (
0#
0%
#2585
b11 *
1#
1%
#2590
b10 "
b10 &
b10 )
b11 (
0#
0%
#2595
b100 *
1#
1%
#2600
b11 "
b11 &
b11 )
b100 (
0#
0%
#2605
b101 *
1#
1%
#2610
b100 "
b100 &
b100 )
b101 (
0#
0%
#2615
b110 *
1#
1%
#2620
b101 "
b101 &
b101 )
b110 (
0#
0%
#2625
b111 *
1#
1%
#2630
b110 "
b110 &
b110 )
b111 (
0#
0%
#2635
b1000 *
1#
1%
#2640
b111 "
b111 &
b111 )
b1000 (
0#
0%
#2645
b1001 *
1#
1%
#2650
b1000 "
b1000 &
b1000 )
b1001 (
0#
0%
